odoo/addons/contract/README.rst
odoo/addons/contract/__init__.py
odoo/addons/contract/__manifest__.py
odoo/addons/contract/controllers/__init__.py
odoo/addons/contract/controllers/main.py
odoo/addons/contract/data/contract_cron.xml
odoo/addons/contract/data/ir_ui_menu.xml
odoo/addons/contract/data/mail_message_subtype.xml
odoo/addons/contract/data/mail_template.xml
odoo/addons/contract/data/template_mail_notification.xml
odoo/addons/contract/i18n/am.po
odoo/addons/contract/i18n/ar.po
odoo/addons/contract/i18n/bg.po
odoo/addons/contract/i18n/bs.po
odoo/addons/contract/i18n/ca.po
odoo/addons/contract/i18n/ca_ES.po
odoo/addons/contract/i18n/contract.pot
odoo/addons/contract/i18n/cs.po
odoo/addons/contract/i18n/da.po
odoo/addons/contract/i18n/de.po
odoo/addons/contract/i18n/el_GR.po
odoo/addons/contract/i18n/en_GB.po
odoo/addons/contract/i18n/es.po
odoo/addons/contract/i18n/es_AR.po
odoo/addons/contract/i18n/es_CL.po
odoo/addons/contract/i18n/es_CO.po
odoo/addons/contract/i18n/es_CR.po
odoo/addons/contract/i18n/es_DO.po
odoo/addons/contract/i18n/es_EC.po
odoo/addons/contract/i18n/es_MX.po
odoo/addons/contract/i18n/es_PY.po
odoo/addons/contract/i18n/es_VE.po
odoo/addons/contract/i18n/et.po
odoo/addons/contract/i18n/eu.po
odoo/addons/contract/i18n/fa.po
odoo/addons/contract/i18n/fi.po
odoo/addons/contract/i18n/fr.po
odoo/addons/contract/i18n/fr_CA.po
odoo/addons/contract/i18n/fr_CH.po
odoo/addons/contract/i18n/fr_FR.po
odoo/addons/contract/i18n/gl.po
odoo/addons/contract/i18n/gl_ES.po
odoo/addons/contract/i18n/he.po
odoo/addons/contract/i18n/hi_IN.po
odoo/addons/contract/i18n/hr.po
odoo/addons/contract/i18n/hr_HR.po
odoo/addons/contract/i18n/hu.po
odoo/addons/contract/i18n/id.po
odoo/addons/contract/i18n/it.po
odoo/addons/contract/i18n/ja.po
odoo/addons/contract/i18n/ko.po
odoo/addons/contract/i18n/lt.po
odoo/addons/contract/i18n/lt_LT.po
odoo/addons/contract/i18n/lv.po
odoo/addons/contract/i18n/mk.po
odoo/addons/contract/i18n/mn.po
odoo/addons/contract/i18n/nb.po
odoo_addon_contract-18.0.2.3.0.dist-info/METADATA
odoo_addon_contract-18.0.2.3.0.dist-info/WHEEL
odoo_addon_contract-18.0.2.3.0.dist-info/top_level.txt
odoo_addon_contract-18.0.2.3.0.dist-info/RECORD
