Metadata-Version: 2.1
Name: odoo-addon-contract
Version: 18.0.2.3.0
Requires-Python: >=3.10
Requires-Dist: odoo==18.0.*
Summary: Recurring - Contracts Management
Home-page: https://github.com/OCA/contract
License: AGPL-3
Author: Tecnativa, ACSONE SA/NV, Odoo Community Association (OCA)
Author-email: support@odoo-community.org
Classifier: Programming Language :: Python
Classifier: Framework :: Odoo
Classifier: Framework :: Odoo :: 18.0
Classifier: License :: OSI Approved :: GNU Affero General Public License v3
Classifier: Development Status :: 5 - Production/Stable
